mopy/__init__.py
mopy/config.py
mopy/constants.py
mopy/core.py
mopy/exceptions.py
mopy/magnitude.py
mopy/plotting.py
mopy/smooth.py
mopy/sourcemodels.py
mopy/sourcemodels_old.py
mopy/utils.py
mopy/version.py
mopy-0.0.0.dist-info/METADATA
mopy-0.0.0.dist-info/WHEEL
mopy-0.0.0.dist-info/top_level.txt
mopy-0.0.0.dist-info/RECORD
