Metadata-Version: 2.1
Name: mopy
Version: 0.0.0
Summary: package to calc source params
Home-page: https://github.com/niosh-mining/obsplus
Author: Derrick Chambers
Author-email: djachambeador@gmail.com
License: GNU Lesser General Public License v3.0 or later (LGPLv3.0+)
Keywords: obsplus
Platform: UNKNOWN
Classifier: Development Status :: 4 - Beta
Classifier: Intended Audience :: Developers
Classifier: License :: OSI Approved :: GNU Lesser General Public License v3 or later (LGPLv3+)
Classifier: Programming Language :: Python :: 3.6
Classifier: Programming Language :: Python :: 3.7
Classifier: Topic :: Scientific/Engineering
Requires-Python: >=3.6
